{
 "actions": [],
 "allow_rename": 1,
 "creation": "2021-12-24 02:58:22.278259",
 "doctype": "DocType",
 "editable_grid": 1,
 "engine": "InnoDB",
 "field_order": [
  "date_dues",
  "amount",
  "paid_amount",
  "is_paid",
  "is_partial_paid",
  "is_late",
  "party_type",
  "party_name"
 ],
 "fields": [
  {
   "allow_in_quick_entry": 1,
   "fieldname": "date_dues",
   "fieldtype": "Date",
   "in_list_view": 1,
   "in_preview": 1,
   "label": "Date dues"
  },
  {
   "allow_in_quick_entry": 1,
   "fieldname": "amount",
   "fieldtype": "Currency",
   "in_list_view": 1,
   "in_preview": 1,
   "label": "Amount "
  },
  {
   "allow_on_submit": 1,
   "fieldname": "party_type",
   "fieldtype": "Select",
   "hidden": 1,
   "label": "Party Type",
   "options": "Purchase Invoice\nSales Invoice\nSalary Slip"
  },
  {
   "allow_on_submit": 1,
   "fieldname": "party_name",
   "fieldtype": "Dynamic Link",
   "label": "Party Name",
   "options": "party_type"
  },
  {
   "allow_in_quick_entry": 1,
   "allow_on_submit": 1,
   "bold": 1,
   "default": "0",
   "fieldname": "is_paid",
   "fieldtype": "Check",
   "in_list_view": 1,
   "in_preview": 1,
   "label": "Is Paid",
   "read_only": 1
  },
  {
   "allow_in_quick_entry": 1,
   "allow_on_submit": 1,
   "bold": 1,
   "default": "0",
   "fieldname": "is_partial_paid",
   "fieldtype": "Check",
   "in_list_view": 1,
   "in_preview": 1,
   "label": "Is Partial Paid",
   "read_only": 1
  },
  {
   "allow_in_quick_entry": 1,
   "allow_on_submit": 1,
   "bold": 1,
   "default": "0",
   "fieldname": "is_late",
   "fieldtype": "Check",
   "in_list_view": 1,
   "in_preview": 1,
   "in_standard_filter": 1,
   "label": "Is Late",
   "read_only": 1
  },
  {
   "fieldname": "paid_amount",
   "fieldtype": "Currency",
   "label": "Paid Amount"
  }
 ],
 "index_web_pages_for_search": 1,
 "istable": 1,
 "links": [],
 "modified": "2022-01-22 00:40:32.804224",
 "modified_by": "Administrator",
 "module": "Contract Payment",
 "name": "Contract Dues",
 "owner": "Administrator",
 "permissions": [],
 "sort_field": "modified",
 "sort_order": "DESC"
}